LICENSE.txt
MANIFEST.in
README
README.md
setup.py
Django_Select2_Py3.egg-info/PKG-INFO
Django_Select2_Py3.egg-info/SOURCES.txt
Django_Select2_Py3.egg-info/dependency_links.txt
Django_Select2_Py3.egg-info/requires.txt
Django_Select2_Py3.egg-info/top_level.txt
django_select2/__init__.py
django_select2/db_client.py
django_select2/fields.py
django_select2/memcache_client.py
django_select2/memcache_wrapped_db_client.py
django_select2/models.py
django_select2/urls.py
django_select2/util.py
django_select2/views.py
django_select2/widgets.py
django_select2/static/css/all.min.css
django_select2/static/css/extra.css
django_select2/static/css/select2-spinner.gif
django_select2/static/css/select2.css
django_select2/static/css/select2.min.css
django_select2/static/css/select2.png
django_select2/static/css/select2x2.png
django_select2/static/js/heavy_data.js
django_select2/static/js/heavy_data.min.js
django_select2/static/js/select2.js
django_select2/static/js/select2.min.js
django_select2/templatetags/__init__.py
django_select2/templatetags/django_select2_tags.py