Metadata-Version: 1.1
Name: Django-Select2-Py3
Version: 4.2.1
Summary: Select2 option fields for Django for Python3
Home-page: https://github.com/applegrew/django-select2
Author: Nirupam Biswas, Nicolas Pantel
Author-email: admin@applegrew.com
License: LICENSE.txt
Platform: UNKNOWN
Classifier: Development Status :: 4 - Beta
Classifier: Environment :: Web Environment
Classifier: Intended Audience :: Developers
Classifier: License :: OSI Approved :: Apache Software License
Classifier: Operating System :: OS Independent
Classifier: Programming Language :: Python
Classifier: Framework :: Django
